vkforge/__init__.py
vkforge/cli.py
vkforge/context.py
vkforge/layout.py
vkforge/mappings.py
vkforge/schema.py
vkforge/shader.py
vkforge/writer.py
vkforge/translators/__init__.py
vkforge/translators/cmake.py
vkforge/translators/core.py
vkforge/translators/func.py
vkforge/translators/layout.py
vkforge/translators/pipeline.py
vkforge/translators/type.py
vkforge/translators/util.py
vkforge-0.5.9.dist-info/licenses/LICENSE
vkforge-0.5.9.dist-info/METADATA
vkforge-0.5.9.dist-info/WHEEL
vkforge-0.5.9.dist-info/entry_points.txt
vkforge-0.5.9.dist-info/top_level.txt
vkforge-0.5.9.dist-info/RECORD
