Metadata-Version: 2.4
Name: vkforge
Version: 0.5.9
Summary: VkForge: A Vulkan User-End API Implementation Generator for Renderer Development
Author-email: Alrick Grandison <alrickgrandison@gmail.com>
License-Expression: MIT
Project-URL: Homepage, https://github.com/Rickodesea/VkForge
Requires-Python: >=3.8
License-File: LICENSE
Requires-Dist: pydantic>=2.0
Requires-Dist: PyYAML>=6.0
Dynamic: license-file
